{"ranking":[{"name":"Afghanistan","value":106598},{"name":"Albania","value":33492},{"name":"Algeria","value":116901},{"name":"Andorra","value":16220},{"name":"Angola","value":67077},{"name":"Argentina","value":183889},{"name":"Armenia","value":97564},{"name":"Australia","value":360009},{"name":"Austria","value":311166},{"name":"Azerbaijan","value":110440},{"name":"Bahrain","value":16221},{"name":"Bangladesh","value":229784},{"name":"Belarus","value":95128},{"name":"Belgium","value":318275},{"name":"Benin","value":61493},{"name":"Bhutan","value":11399},{"name":"Bolivia","value":63912},{"name":"Bosnia and Herz.","value":788},{"name":"Botswana","value":19585},{"name":"Brazil","value":240038},{"name":"Bulgaria","value":222703},{"name":"Burkina Faso","value":6280},{"name":"Burundi","value":17056},{"name":"Cambodia","value":56143},{"name":"Cameroon","value":139085},{"name":"Canada","value":399657},{"name":"Chad","value":3745},{"name":"Chile","value":141327},{"name":"China","value":335173},{"name":"Colombia","value":149779},{"name":"Congo","value":29724},{"name":"Croatia","value":142799},{"name":"Cuba","value":63057},{"name":"Cyprus","value":88429},{"name":"Czechia","value":320388},{"name":"Denmark","value":267010},{"name":"Dominican Rep.","value":39117},{"name":"Ecuador","value":122800},{"name":"Egypt","value":246120},{"name":"El Salvador","value":49973},{"name":"Estonia","value":21711},{"name":"Ethiopia","value":346214},{"name":"Finland","value":283042},{"name":"France","value":530191},{"name":"Georgia","value":146838},{"name":"Germany","value":602971},{"name":"Ghana","value":294509},{"name":"Greece","value":168256},{"name":"Guatemala","value":85052},{"name":"Honduras","value":42972},{"name":"Hong Kong","value":190249},{"name":"Hungary","value":204125},{"name":"Iceland","value":59015},{"name":"India","value":287228},{"name":"Indonesia","value":346685},{"name":"Iran","value":230866},{"name":"Iraq","value":61465},{"name":"Ireland","value":169701},{"name":"Israel","value":232994},{"name":"Italy","value":362295},{"name":"Jamaica","value":53431},{"name":"Japan","value":518906},{"name":"Jordan","value":66374},{"name":"Kazakhstan","value":81377},{"name":"Kenya","value":438426},{"name":"Kuwait","value":15882},{"name":"Laos","value":5995},{"name":"Latvia","value":66302},{"name":"Lithuania","value":87469},{"name":"Luxembourg","value":62438},{"name":"Madagascar","value":81956},{"name":"Malawi","value":45091},{"name":"Taiwan","value":300796}]}
